commoditycategory/__init__.py
commoditycategory/commoditycategory.py
commditycategory-0.9.4.dist-info/LICENSE
commditycategory-0.9.4.dist-info/METADATA
commditycategory-0.9.4.dist-info/WHEEL
commditycategory-0.9.4.dist-info/top_level.txt
commditycategory-0.9.4.dist-info/RECORD
